ovos_ddg_solver/__init__.py
ovos_ddg_solver/version.py
ovos_ddg_solver/locale/ca-es/MiscBlacklist.voc
ovos_ddg_solver/locale/ca-es/More.voc
ovos_ddg_solver/locale/ca-es/Weather.voc
ovos_ddg_solver/locale/ca-es/age_at_death.intent
ovos_ddg_solver/locale/ca-es/alma_mater.intent
ovos_ddg_solver/locale/ca-es/birthdate.intent
ovos_ddg_solver/locale/ca-es/born.intent
ovos_ddg_solver/locale/ca-es/children.intent
ovos_ddg_solver/locale/ca-es/died.intent
ovos_ddg_solver/locale/ca-es/education.intent
ovos_ddg_solver/locale/ca-es/fields.intent
ovos_ddg_solver/locale/ca-es/known_for.intent
ovos_ddg_solver/locale/ca-es/no_answer.dialog
ovos_ddg_solver/locale/ca-es/official_website.intent
ovos_ddg_solver/locale/ca-es/resting_place.intent
ovos_ddg_solver/locale/ca-es/search_duck.intent
ovos_ddg_solver/locale/ca-es/skill.json
ovos_ddg_solver/locale/ca-es/thats all.dialog
ovos_ddg_solver/locale/ca-es/thesis.intent
ovos_ddg_solver/locale/ca-es/who.intent
ovos_ddg_solver/locale/da-dk/More.voc
ovos_ddg_solver/locale/da-dk/age_at_death.intent
ovos_ddg_solver/locale/da-dk/alma_mater.intent
ovos_ddg_solver/locale/da-dk/birthdate.intent
ovos_ddg_solver/locale/da-dk/born.intent
ovos_ddg_solver/locale/da-dk/children.intent
ovos_ddg_solver/locale/da-dk/died.intent
ovos_ddg_solver/locale/da-dk/education.intent
ovos_ddg_solver/locale/da-dk/fields.intent
ovos_ddg_solver/locale/da-dk/known_for.intent
ovos_ddg_solver/locale/da-dk/no_answer.dialog
ovos_ddg_solver/locale/da-dk/official_website.intent
ovos_ddg_solver/locale/da-dk/resting_place.intent
ovos_ddg_solver/locale/da-dk/search_duck.intent
ovos_ddg_solver/locale/da-dk/skill.json
ovos_ddg_solver/locale/da-dk/thats all.dialog
ovos_ddg_solver/locale/da-dk/thesis.intent
ovos_ddg_solver/locale/da-dk/who.intent
ovos_ddg_solver/locale/de-de/MiscBlacklist.voc
ovos_ddg_solver/locale/de-de/More.voc
ovos_ddg_solver/locale/de-de/Weather.voc
ovos_ddg_solver/locale/de-de/age_at_death.intent
ovos_ddg_solver/locale/de-de/alma_mater.intent
ovos_ddg_solver_plugin-0.0.2a3.dist-info/METADATA
ovos_ddg_solver_plugin-0.0.2a3.dist-info/WHEEL
ovos_ddg_solver_plugin-0.0.2a3.dist-info/entry_points.txt
ovos_ddg_solver_plugin-0.0.2a3.dist-info/top_level.txt
ovos_ddg_solver_plugin-0.0.2a3.dist-info/RECORD
