Metadata-Version: 2.4
Name: ovos_ddg_solver_plugin
Version: 0.0.2a3
Summary: ovos duckduckgo plugin
Home-page: https://github.com/OpenVoiceOS/ovos-solver-ddg-plugin
Author: JarbasAi
Author-email: jarbasai@mailfence.com
License: Apache-2.0
Keywords: ovos ddg search plugin
Requires-Dist: ovos-utils<1.0.0,>=0.7.0
Requires-Dist: ovos-plugin-manager<3.0.0,>=2.1.0
Requires-Dist: ovos-bus-client>=1.0.1
Requires-Dist: RAKEkeywords
Requires-Dist: requests
Requires-Dist: langcodes
Requires-Dist: ovos-date-parser
Dynamic: author
Dynamic: author-email
Dynamic: description
Dynamic: description-content-type
Dynamic: home-page
Dynamic: keywords
Dynamic: license
Dynamic: requires-dist
Dynamic: summary
